resource_abstractor_client/__init__.py
resource_abstractor_client/app_operations.py
resource_abstractor_client/client_helper.py
resource_abstractor_client/cluster_operations.py
resource_abstractor_client/job_operations.py
resource_abstractor_client-0.1.3.dist-info/METADATA
resource_abstractor_client-0.1.3.dist-info/WHEEL
resource_abstractor_client-0.1.3.dist-info/RECORD
