Metadata-Version: 2.1
Name: resource_abstractor_client
Version: 0.1.3
Summary: TODO
Author: Mahmoud Elkodary
Requires-Python: >=3.10,<4.0
Classifier: Programming Language :: Python :: 3
Classifier: Programming Language :: Python :: 3.10
Classifier: Programming Language :: Python :: 3.11
Classifier: Programming Language :: Python :: 3.12
Requires-Dist: requests (>=2.27.1,<3.0.0)
